{
  "case": {
    "problem": "gl",
    "backend": "fenics",
    "level": 7,
    "out": "/home/michal/repos/fenics_nonlinear_energies/artifacts/reproduction/2026-03-15_refactor_stage2b_final/full/gl_final_suite/fenics_custom_l7_np8.json",
    "quiet": true,
    "save_history": true,
    "save_linear_timing": true,
    "steps": 1,
    "start_step": 1,
    "total_steps": 24,
    "ksp_type": "gmres",
    "pc_type": "hypre",
    "ksp_rtol": 0.001,
    "ksp_max_it": 200,
    "profile": "reference",
    "coloring_trials": 10,
    "nproc_threads": 1,
    "hvp_eval_mode": "sequential",
    "element_reorder_mode": null,
    "local_hessian_mode": null,
    "tolf": 1e-06,
    "tolg": 1e-05,
    "tolg_rel": 0.001,
    "tolx_rel": 0.001,
    "tolx_abs": 1e-10,
    "maxit": 100,
    "step_time_limit_s": null,
    "linesearch_a": -0.5,
    "linesearch_b": 2.0,
    "linesearch_tol": 0.001,
    "use_trust_region": false,
    "trust_radius_init": 1.0,
    "trust_radius_min": 1e-08,
    "trust_radius_max": 1000000.0,
    "trust_shrink": 0.5,
    "trust_expand": 1.5,
    "trust_eta_shrink": 0.05,
    "trust_eta_expand": 0.75,
    "trust_max_reject": 6,
    "trust_subproblem_line_search": false,
    "local_coloring": true,
    "retry_on_failure": false,
    "pc_setup_on_ksp_cap": false,
    "use_near_nullspace": true,
    "reorder": null,
    "gamg_threshold": 0.05,
    "gamg_agg_nsmooths": 1,
    "gamg_set_coordinates": true
  },
  "result": {
    "mesh_level": 7,
    "total_dofs": 66049,
    "free_dofs": 65916,
    "setup_time": 0.210803,
    "solve_time_total": 0.429102,
    "total_time": 0.64002,
    "steps": [
      {
        "step": 1,
        "time": 0.429102,
        "nit": 8,
        "linear_iters": 34,
        "energy": 0.34566226111288545,
        "message": "Converged (energy, step, gradient)",
        "attempt": "primary",
        "ksp_rtol_used": 0.001,
        "ksp_max_it_used": 200,
        "linesearch_interval_used": [
          -0.5,
          2.0
        ],
        "history": [
          {
            "it": 1,
            "energy": 0.5590074635208717,
            "dE": 0.10630221894586223,
            "grad_norm": 0.00370460376965253,
            "grad_target": 1e-05,
            "grad_norm_post": NaN,
            "alpha": -0.27055941146961116,
            "ksp_its": 9,
            "ls_evals": 19,
            "ls_repaired": false,
            "used_gradient_fallback": false,
            "accepted_step": true,
            "step_norm": 64.93711824603801,
            "step_rel": 0.507321236297172,
            "pred_reduction": NaN,
            "actual_reduction": NaN,
            "trust_rejects": 0,
            "t_grad": 0.0012895979452878237,
            "t_hess": 0.04904267005622387,
            "t_ls": 0.014779544086195529,
            "t_update": 2.2844062186777592e-05,
            "t_iter": 0.06518317898735404,
            "trust_radius": 1.0,
            "trust_ratio": NaN,
            "trust_qp": NaN
          },
          {
            "it": 2,
            "energy": 0.5101984273298092,
            "dE": 0.04880903619106247,
            "grad_norm": 0.004045335238364926,
            "grad_target": 1e-05,
            "grad_norm_post": NaN,
            "alpha": 0.33147294517641523,
            "ksp_its": 6,
            "ls_evals": 19,
            "ls_repaired": false,
            "used_gradient_fallback": false,
            "accepted_step": true,
            "step_norm": 51.65564341235554,
            "step_rel": 0.31929934659384185,
            "pred_reduction": NaN,
            "actual_reduction": NaN,
            "trust_rejects": 0,
            "t_grad": 0.0012611850397661328,
            "t_hess": 0.03886447299737483,
            "t_ls": 0.018557501956820488,
            "t_update": 2.3785047233104706e-05,
            "t_iter": 0.058751211035996675,
            "trust_radius": 1.0,
            "trust_ratio": NaN,
            "trust_qp": NaN
          },
          {
            "it": 3,
            "energy": 0.44967856766345143,
            "dE": 0.06051985966635781,
            "grad_norm": 0.002243980061417418,
            "grad_target": 1e-05,
            "grad_norm_post": NaN,
            "alpha": -0.29481905381379636,
            "ksp_its": 5,
            "ls_evals": 19,
            "ls_repaired": false,
            "used_gradient_fallback": false,
            "accepted_step": true,
            "step_norm": 63.187743728524964,
            "step_rel": 0.337849546838511,
            "pred_reduction": NaN,
            "actual_reduction": NaN,
            "trust_rejects": 0,
            "t_grad": 0.0012099880259484053,
            "t_hess": 0.03705683606676757,
            "t_ls": 0.017491378937847912,
            "t_update": 2.2003077901899815e-05,
            "t_iter": 0.05582000606227666,
            "trust_radius": 1.0,
            "trust_ratio": NaN,
            "trust_qp": NaN
          },
          {
            "it": 4,
            "energy": 0.3994704838306068,
            "dE": 0.05020808383284464,
            "grad_norm": 0.0035189545818461367,
            "grad_target": 1e-05,
            "grad_norm_post": NaN,
            "alpha": 0.08458877927871977,
            "ksp_its": 5,
            "ls_evals": 19,
            "ls_repaired": false,
            "used_gradient_fallback": false,
            "accepted_step": true,
            "step_norm": 46.221388771561095,
            "step_rel": 0.2317477118278394,
            "pred_reduction": NaN,
            "actual_reduction": NaN,
            "trust_rejects": 0,
            "t_grad": 0.0012172500137239695,
            "t_hess": 0.038284289999864995,
            "t_ls": 0.014804781065322459,
            "t_update": 1.8778955563902855e-05,
            "t_iter": 0.05436748301144689,
            "trust_radius": 1.0,
            "trust_ratio": NaN,
            "trust_qp": NaN
          },
          {
            "it": 5,
            "energy": 0.3593478630617263,
            "dE": 0.04012262076888051,
            "grad_norm": 0.0034693628440023057,
            "grad_target": 1e-05,
            "grad_norm_post": NaN,
            "alpha": 0.353364927379929,
            "ksp_its": 3,
            "ls_evals": 19,
            "ls_repaired": false,
            "used_gradient_fallback": false,
            "accepted_step": true,
            "step_norm": 35.02318234846958,
            "step_rel": 0.1674169338370883,
            "pred_reduction": NaN,
            "actual_reduction": NaN,
            "trust_rejects": 0,
            "t_grad": 0.0012204039376229048,
            "t_hess": 0.03280887100845575,
            "t_ls": 0.014655917999334633,
            "t_update": 2.2504013031721115e-05,
            "t_iter": 0.04876130702905357,
            "trust_radius": 1.0,
            "trust_ratio": NaN,
            "trust_qp": NaN
          },
          {
            "it": 6,
            "energy": 0.3458368932025319,
            "dE": 0.013510969859194366,
            "grad_norm": 0.0021465552209874827,
            "grad_target": 1e-05,
            "grad_norm_post": NaN,
            "alpha": 1.00224899252863,
            "ksp_its": 2,
            "ls_evals": 19,
            "ls_repaired": false,
            "used_gradient_fallback": false,
            "accepted_step": true,
            "step_norm": 13.947621803492492,
            "step_rel": 0.06412582253707122,
            "pred_reduction": NaN,
            "actual_reduction": NaN,
            "trust_rejects": 0,
            "t_grad": 0.0012224169913679361,
            "t_hess": 0.030378728988580406,
            "t_ls": 0.017487794044427574,
            "t_update": 2.347491681575775e-05,
            "t_iter": 0.04914944001939148,
            "trust_radius": 1.0,
            "trust_ratio": NaN,
            "trust_qp": NaN
          },
          {
            "it": 7,
            "energy": 0.34566227738893884,
            "dE": 0.00017461581359307088,
            "grad_norm": 0.00021586214613080113,
            "grad_target": 1e-05,
            "grad_norm_post": NaN,
            "alpha": 1.0214427797835948,
            "ksp_its": 2,
            "ls_evals": 19,
            "ls_repaired": false,
            "used_gradient_fallback": false,
            "accepted_step": true,
            "step_norm": 1.8158516306929593,
            "step_rel": 0.008237585172882495,
            "pred_reduction": NaN,
            "actual_reduction": NaN,
            "trust_rejects": 0,
            "t_grad": 0.001225571963004768,
            "t_hess": 0.029892447986640036,
            "t_ls": 0.014602796989493072,
            "t_update": 2.297398168593645e-05,
            "t_iter": 0.045780655927956104,
            "trust_radius": 1.0,
            "trust_ratio": NaN,
            "trust_qp": NaN
          },
          {
            "it": 8,
            "energy": 0.34566226111288545,
            "dE": 1.6276053393937673e-08,
            "grad_norm": 2.083549596026195e-06,
            "grad_target": 1e-05,
            "grad_norm_post": 3.859914664840549e-09,
            "alpha": 1.000416148939007,
            "ksp_its": 2,
            "ls_evals": 19,
            "ls_repaired": false,
            "used_gradient_fallback": false,
            "accepted_step": true,
            "step_norm": 0.017568129562644152,
            "step_rel": 8.016113757579755e-05,
            "pred_reduction": NaN,
            "actual_reduction": NaN,
            "trust_rejects": 0,
            "t_grad": 0.001222298014909029,
            "t_hess": 0.029955793055705726,
            "t_ls": 0.01750229496974498,
            "t_update": 2.1892949007451534e-05,
            "t_iter": 0.0487411969806999,
            "trust_radius": 1.0,
            "trust_ratio": NaN,
            "trust_qp": NaN
          }
        ],
        "linear_timing": [
          {
            "assemble_total_time": 0.004569748067297041,
            "setop_time": 4.927976988255978e-06,
            "set_tolerances_time": 1.9529834389686584e-06,
            "pc_setup_time": 0.021974426927044988,
            "solve_time": 0.02236981096211821,
            "linear_total_time": 0.04892086691688746,
            "ksp_its": 9,
            "ksp_reason_code": 2,
            "ksp_reason_name": "CONVERGED_RTOL",
            "ksp_residual_norm": 34.70970965234881,
            "rhs_norm": 0.00370460376965253
          },
          {
            "assemble_total_time": 0.004061473999172449,
            "setop_time": 1.7220154404640198e-06,
            "set_tolerances_time": 2.0329607650637627e-06,
            "pc_setup_time": 0.019675040966831148,
            "solve_time": 0.015011581941507757,
            "linear_total_time": 0.03875185188371688,
            "ksp_its": 6,
            "ksp_reason_code": 2,
            "ksp_reason_name": "CONVERGED_RTOL",
            "ksp_residual_norm": 0.6187598831689025,
            "rhs_norm": 0.004045335238364926
          },
          {
            "assemble_total_time": 0.004073843010701239,
            "setop_time": 1.4218967407941818e-06,
            "set_tolerances_time": 1.5619443729519844e-06,
            "pc_setup_time": 0.01980149105656892,
            "solve_time": 0.0130601100390777,
            "linear_total_time": 0.036938427947461605,
            "ksp_its": 5,
            "ksp_reason_code": 2,
            "ksp_reason_name": "CONVERGED_RTOL",
            "ksp_residual_norm": 1.9673464188876226,
            "rhs_norm": 0.002243980061417418
          },
          {
            "assemble_total_time": 0.004033891949802637,
            "setop_time": 1.1320225894451141e-06,
            "set_tolerances_time": 1.7120037227869034e-06,
            "pc_setup_time": 0.02034605003427714,
            "solve_time": 0.013801753986626863,
            "linear_total_time": 0.038184539997018874,
            "ksp_its": 5,
            "ksp_reason_code": 2,
            "ksp_reason_name": "CONVERGED_RTOL",
            "ksp_residual_norm": 0.18199640505770925,
            "rhs_norm": 0.0035189545818461367
          },
          {
            "assemble_total_time": 0.0040405429899692535,
            "setop_time": 1.2509990483522415e-06,
            "set_tolerances_time": 1.5220139175653458e-06,
            "pc_setup_time": 0.019858737010508776,
            "solve_time": 0.008796982001513243,
            "linear_total_time": 0.03269903501495719,
            "ksp_its": 3,
            "ksp_reason_code": 2,
            "ksp_reason_name": "CONVERGED_RTOL",
            "ksp_residual_norm": 0.027951647940368446,
            "rhs_norm": 0.0034693628440023057
          },
          {
            "assemble_total_time": 0.004028744995594025,
            "setop_time": 1.2509990483522415e-06,
            "set_tolerances_time": 1.2209638953208923e-06,
            "pc_setup_time": 0.019558154977858067,
            "solve_time": 0.006668142043054104,
            "linear_total_time": 0.030257513979449868,
            "ksp_its": 2,
            "ksp_reason_code": 2,
            "ksp_reason_name": "CONVERGED_RTOL",
            "ksp_residual_norm": 0.0049736519461268894,
            "rhs_norm": 0.0021465552209874827
          },
          {
            "assemble_total_time": 0.004034745041280985,
            "setop_time": 1.451931893825531e-06,
            "set_tolerances_time": 1.7830170691013336e-06,
            "pc_setup_time": 0.019135379930958152,
            "solve_time": 0.006604507099837065,
            "linear_total_time": 0.02977786702103913,
            "ksp_its": 2,
            "ksp_reason_code": 2,
            "ksp_reason_name": "CONVERGED_RTOL",
            "ksp_residual_norm": 0.00040439522649507594,
            "rhs_norm": 0.00021586214613080113
          },
          {
            "assemble_total_time": 0.004023598041385412,
            "setop_time": 1.6529811546206474e-06,
            "set_tolerances_time": 1.552049070596695e-06,
            "pc_setup_time": 0.01927912700921297,
            "solve_time": 0.00654470594599843,
            "linear_total_time": 0.02985063602682203,
            "ksp_its": 2,
            "ksp_reason_code": 2,
            "ksp_reason_name": "CONVERGED_RTOL",
            "ksp_residual_norm": 4.60469575240367e-06,
            "rhs_norm": 2.083549596026195e-06
          }
        ]
      }
    ],
    "metadata": {
      "nprocs": 8,
      "problem": {
        "name": "GinzburgLandau2D",
        "eps": 0.01
      },
      "linear_solver": {
        "ksp_type": "gmres",
        "pc_type": "hypre",
        "ksp_rtol": 0.001,
        "ksp_max_it": 200,
        "pc_setup_on_ksp_cap": false,
        "gamg_threshold": 0.05,
        "gamg_agg_nsmooths": 1,
        "gamg_set_coordinates": true,
        "assembly_mode": "fenics",
        "assembler": "FEniCSFormAssembly",
        "distribution_strategy": "dolfinx_mesh_partition",
        "trust_subproblem_solver": "direct_linear_solve",
        "trust_subproblem_line_search": false
      },
      "newton": {
        "tolf": 1e-06,
        "tolg": 1e-05,
        "tolg_rel": 0.001,
        "tolx_rel": 0.001,
        "tolx_abs": 1e-10,
        "maxit": 100,
        "require_all_convergence": true,
        "fail_on_nonfinite": true,
        "linesearch_interval": [
          -0.5,
          2.0
        ],
        "linesearch_tol": 0.001,
        "trust_region": false,
        "trust_radius_init": 1.0,
        "trust_radius_min": 1e-08,
        "trust_radius_max": 1000000.0,
        "trust_subproblem_line_search": false,
        "step_time_limit_s": null
      }
    }
  }
}