{
  "command": "/usr/bin/mpiexec -n 32 /home/michal/repos/fenics_nonlinear_energies/.venv/bin/python -u src/problems/hyperelasticity/jax_petsc/solve_HE_dof.py --level 4 --steps 24 --total_steps 24 --profile performance --ksp_type stcg --pc_type gamg --ksp_rtol 1e-1 --ksp_max_it 30 --gamg_threshold 0.05 --gamg_agg_nsmooths 1 --gamg_set_coordinates --use_near_nullspace --no-pc_setup_on_ksp_cap --assembly_mode element --element_reorder_mode block_xyz --local_hessian_mode element --local_coloring --tolf 1e-4 --tolg 1e-3 --tolg_rel 1e-3 --tolx_rel 1e-3 --tolx_abs 1e-10 --maxit 100 --linesearch_a -0.5 --linesearch_b 2.0 --linesearch_tol 1e-1 --use_trust_region --trust_radius_init 0.5 --trust_radius_min 1e-8 --trust_radius_max 1e6 --trust_shrink 0.5 --trust_expand 1.5 --trust_eta_shrink 0.05 --trust_eta_expand 0.75 --trust_max_reject 6 --trust_subproblem_line_search --nproc 1 --quiet --out overview/img/runs/hyperelasticity/sample_render/jax_petsc_element_l4_np32/output.json --state-out overview/img/runs/hyperelasticity/sample_render/jax_petsc_element_l4_np32/state.npz",
  "command_argv": [
    "/usr/bin/mpiexec",
    "-n",
    "32",
    "/home/michal/repos/fenics_nonlinear_energies/.venv/bin/python",
    "-u",
    "src/problems/hyperelasticity/jax_petsc/solve_HE_dof.py",
    "--level",
    "4",
    "--steps",
    "24",
    "--total_steps",
    "24",
    "--profile",
    "performance",
    "--ksp_type",
    "stcg",
    "--pc_type",
    "gamg",
    "--ksp_rtol",
    "1e-1",
    "--ksp_max_it",
    "30",
    "--gamg_threshold",
    "0.05",
    "--gamg_agg_nsmooths",
    "1",
    "--gamg_set_coordinates",
    "--use_near_nullspace",
    "--no-pc_setup_on_ksp_cap",
    "--assembly_mode",
    "element",
    "--element_reorder_mode",
    "block_xyz",
    "--local_hessian_mode",
    "element",
    "--local_coloring",
    "--tolf",
    "1e-4",
    "--tolg",
    "1e-3",
    "--tolg_rel",
    "1e-3",
    "--tolx_rel",
    "1e-3",
    "--tolx_abs",
    "1e-10",
    "--maxit",
    "100",
    "--linesearch_a",
    "-0.5",
    "--linesearch_b",
    "2.0",
    "--linesearch_tol",
    "1e-1",
    "--use_trust_region",
    "--trust_radius_init",
    "0.5",
    "--trust_radius_min",
    "1e-8",
    "--trust_radius_max",
    "1e6",
    "--trust_shrink",
    "0.5",
    "--trust_expand",
    "1.5",
    "--trust_eta_shrink",
    "0.05",
    "--trust_eta_expand",
    "0.75",
    "--trust_max_reject",
    "6",
    "--trust_subproblem_line_search",
    "--nproc",
    "1",
    "--quiet",
    "--out",
    "overview/img/runs/hyperelasticity/sample_render/jax_petsc_element_l4_np32/output.json",
    "--state-out",
    "overview/img/runs/hyperelasticity/sample_render/jax_petsc_element_l4_np32/state.npz"
  ],
  "cwd": "/home/michal/repos/fenics_nonlinear_energies",
  "duration_s": 515.4617472330574,
  "exit_code": 0,
  "finished_at": "2026-03-17T03:07:46Z",
  "log_path": "/home/michal/repos/fenics_nonlinear_energies/overview/img/runs/hyperelasticity/sample_render/jax_petsc_element_l4_np32/run.log",
  "notes": "High-resolution HyperElasticity publication render on the validated L4, np32 JAX+PETSc element case",
  "outputs": [
    "/home/michal/repos/fenics_nonlinear_energies/overview/img/runs/hyperelasticity/sample_render/jax_petsc_element_l4_np32/output.json",
    "/home/michal/repos/fenics_nonlinear_energies/overview/img/runs/hyperelasticity/sample_render/jax_petsc_element_l4_np32/state.npz"
  ],
  "skipped": true,
  "started_at": "2026-03-17T02:59:10Z",
  "success": true
}
